wumpy/rest/__init__.py
wumpy/rest/_config.py
wumpy/rest/_errors.py
wumpy/rest/_ratelimiter.py
wumpy/rest/_requester.py
wumpy/rest/_route.py
wumpy/rest/_utils.py
wumpy/rest/py.typed
wumpy/rest/endpoints/__init__.py
wumpy/rest/endpoints/_channel.py
wumpy/rest/endpoints/_commands.py
wumpy/rest/endpoints/_gateway.py
wumpy/rest/endpoints/_guild.py
wumpy/rest/endpoints/_guild_template.py
wumpy/rest/endpoints/_interactions.py
wumpy/rest/endpoints/_sticker.py
wumpy/rest/endpoints/_user.py
wumpy/rest/endpoints/_webhook.py
wumpy_rest-0.3.0.dist-info/WHEEL
wumpy_rest-0.3.0.dist-info/METADATA
wumpy_rest-0.3.0.dist-info/RECORD
